MassSpecJing/__init__.py
MassSpecJing/executor.py
MassSpecJing-0.0.1.dist-info/METADATA
MassSpecJing-0.0.1.dist-info/WHEEL
MassSpecJing-0.0.1.dist-info/top_level.txt
MassSpecJing-0.0.1.dist-info/RECORD
